dbutils/__init__.py
dbutils/dbutils.py
dbutils_gonzalo123-1.3.11.dist-info/LICENSE
dbutils_gonzalo123-1.3.11.dist-info/METADATA
dbutils_gonzalo123-1.3.11.dist-info/WHEEL
dbutils_gonzalo123-1.3.11.dist-info/top_level.txt
dbutils_gonzalo123-1.3.11.dist-info/RECORD
