Metadata-Version: 2.1
Name: dbutils-gonzalo123
Version: 1.3.11
Summary: psycopg2 db utils
Home-page: https://github.com/gonzalo123/dbutils
Author: Gonzalo Ayuso
Author-email: gonzalo123@gmail.com
License: MIT
Keywords: psycopg2
Platform: UNKNOWN
Classifier: Programming Language :: Python :: 3
Classifier: License :: OSI Approved :: MIT License
Classifier: Operating System :: OS Independent
Requires-Python: >=3.5
Requires-Dist: psycopg2-binary (>=2.8.6)
